sqlite_utils_sqlite_http/__init__.py
sqlite_utils_sqlite_http/version.py
sqlite_utils_sqlite_http-0.1.1.dist-info/METADATA
sqlite_utils_sqlite_http-0.1.1.dist-info/WHEEL
sqlite_utils_sqlite_http-0.1.1.dist-info/entry_points.txt
sqlite_utils_sqlite_http-0.1.1.dist-info/top_level.txt
sqlite_utils_sqlite_http-0.1.1.dist-info/RECORD
