Metadata-Version: 2.1
Name: sqlite-utils-sqlite-http
Version: 0.1.1
Summary: TODO
Author: Alex Garcia
License: Apache-2.0
Project-URL: Homepage, https://github.com/asg017/sqlite-http
Project-URL: Changelog, https://github.com/asg017/sqlite-http/releases
Project-URL: Issues, https://github.com/asg017/sqlite-http/issues
Requires-Dist: sqlite-utils
Requires-Dist: sqlite-http
